migrations/__init__.py
evercycle_models-1.0.0.dist-info/METADATA
evercycle_models-1.0.0.dist-info/WHEEL
evercycle_models-1.0.0.dist-info/top_level.txt
evercycle_models-1.0.0.dist-info/RECORD
